{
  "version": 1,
  "source": {
    "path": "integration/fixtures/app-behavior/ast-type-coverage/ts-import-equals/input.ts",
    "language": "ts"
  },
  "direction": "RL",
  "elements": [
    {
      "type": "node",
      "id": "n_scope_0_x_34",
      "name": "x",
      "line": 0,
      "endLine": null,
      "isJsxElement": false,
      "unused": false,
      "kind": "SyntheticImplicitGlobal"
    },
    {
      "type": "node",
      "id": "module_root",
      "kind": "SyntheticModuleSink",
      "name": "module",
      "line": 0,
      "endLine": null,
      "isJsxElement": false,
      "unused": false
    }
  ],
  "edges": [
    {
      "from": "n_scope_0_x_34",
      "to": "module_root",
      "label": "read"
    }
  ],
  "boundaryEdges": [],
  "pruning": null
}
